AUTHORS
ChangeLog
LICENSE
README.md
requirements.txt
setup.cfg
setup.py
image_utils/__init__.py
image_utils/ceph.py
image_utils/errors.py
image_utils/fish.py
image_utils/logger.py
image_utils.egg-info/PKG-INFO
image_utils.egg-info/SOURCES.txt
image_utils.egg-info/dependency_links.txt
image_utils.egg-info/not-zip-safe
image_utils.egg-info/pbr.json
image_utils.egg-info/requires.txt
image_utils.egg-info/top_level.txt